ScanLHA/EditLHA.py
ScanLHA/MergeLHA.py
ScanLHA/PlotLHA.py
ScanLHA/ScanLHA.py
ScanLHA/__init__.py
ScanLHA/config.py
ScanLHA/runner.py
ScanLHA/scan.py
ScanLHA/slha.py
ScanLHA/configs/SPheno.yml
scanlha-0.6.dist-info/entry_points.txt
scanlha-0.6.dist-info/LICENSE
scanlha-0.6.dist-info/WHEEL
scanlha-0.6.dist-info/METADATA
scanlha-0.6.dist-info/RECORD
