Metadata-Version: 2.1
Name: ScanLHA
Version: 0.6
Summary: Perform parameter scans with HEP tools that use (not only) (S)LHA in- and output.
Home-page: https://github.com/martingabelmann/ScanLHA
Author: Martin Gabelmann
Author-email: martin@gabelmann.biz
Classifier: License :: OSI Approved :: GNU General Public License v3 or later (GPLv3+)
Requires-Dist: pylha
Requires-Dist: numpy
Requires-Dist: ipython
Requires-Dist: tqdm
Requires-Dist: pandas
Requires-Dist: matplotlib
Requires-Dist: PyYAML
